LogDefer.py
setup.py
LogDefer.egg-info/PKG-INFO
LogDefer.egg-info/SOURCES.txt
LogDefer.egg-info/dependency_links.txt
LogDefer.egg-info/top_level.txt
LogDefer.egg-info/zip-safe