Metadata-Version: 1.0
Name: LogDefer
Version: 0.1.1
Summary: Structured Logging for Python
Home-page: https://github.com/mikep/LogDefer
Author: Michael Pucyk
Author-email: michael.pucyk@gmail.com
License: UNKNOWN
Keywords: structured logging log logdefer
Platform: UNKNOWN
